python_shellrechargeev-0.1.6.dist-info/METADATA
python_shellrechargeev-0.1.6.dist-info/WHEEL
python_shellrechargeev-0.1.6.dist-info/licenses/LICENSE
shellrechargeev/__init__.py
shellrechargeev/models.py
python_shellrechargeev-0.1.6.dist-info/RECORD
