Metadata-Version: 2.1
Name: python-shellrechargeev
Version: 0.1.6
Summary: Python 3 package to retrieve public EV charger data from Shell Recharge
Author-Email: cyberjunky <ron@cyberjunky.nl>
License: MIT
Classifier: Programming Language :: Python :: 3.10
Classifier: License :: OSI Approved :: GNU General Public License v3 or later (GPLv3+)
Requires-Python: >=3.10
Requires-Dist: aiohttp
Requires-Dist: yarl
Requires-Dist: pydantic<3.0.0,>=1.0.0
